pedesign/__init__.py
pedesign/needle.py
pedesign/pe-designer.py
pedesign-1.0.dist-info/LICENSE.txt
pedesign-1.0.dist-info/METADATA
pedesign-1.0.dist-info/WHEEL
pedesign-1.0.dist-info/top_level.txt
pedesign-1.0.dist-info/RECORD
