Metadata-Version: 2.1
Name: pedesign
Version: 1.0
Summary: Prime editing tools that consist of a reverse transcriptase linked with Cas9 nickase are capable of generating targeted insertions, deletions
Home-page: https://github.com/Gue-ho/PE-Designer
Classifier: Programming Language :: Python :: 3
Classifier: Operating System :: OS Independent
License-File: LICENSE.txt
